{"pbaThMLtSXarJZIthATwfg==":"mbr-1046x616.jpg","nR4hY4m6vt0cnJslO65S9A==":"mbr-1046x697.jpg","T2PaFRXsafyOwMXmq1WErg==":"mbr-1046x707.jpg","EPcdI5Pg7RUY+o8Ee0Yk6A==":"mbr-1920x1441.jpg","Dl9EtJM2JcRSCS8IeJx/XA==":"mbr-1920x1280.jpg","eWWFKQtTTIO9Gx8ww7woJw==":"mbr-1920x1228.jpg","vER/3JbYwEJb8/HgdGIZHA==":"mbr-1-1920x1280.jpg","DsUbWYXD9Ez6cPU1SkfxrQ==":"mbr-2-1920x1280.jpg","DIRliaYglMKPENn4r8w4IA==":"img-20180119-wa0014-192x176.jpg","ifNL0MPmmd6UHpUOaAG4bA==":"mbr-436x291.jpg","ihlkf69UyfSmhSyJ1Jvc6w==":"jumbotron.jpg","biTg9uSHQuNpiykn5/XvAg==":"mbr-3-1920x1280.jpg","lI99+G8l3V3fpfFsmlGYXw==":"mbr-676x451.jpg","xKU+Ibl7mDk4sQs4CuCT5g==":"img-20180119-wa0014-1-192x176.jpg","Os1hpkyKHdJTZJYYSjSiXg==":"01-1.jpg","0OOE1Usrtktm437Z/qTMRQ==":"background2-1.jpg","PObCDLO18OyG8qjHAHrcIQ==":"mbr-1920x1357.jpg","9/7eTJXx2IAKOn0xgMLVIg==":"structural%20reforms-1280x720.jpg","M0BmPc+RcTW4d5L80GQHlg==":"structural%20reforms-1280x720.jpg","65ouWgP0qJRd0iFB5njitw==":"structural%20reforms-1280x720.jpg","h14oMFHa9l0czp4Hzp5TVA==":"structural%20reforms-1280x720.jpg","X/kiCLSP+fLCDPtIrDDDyg==":"structural%20reforms-1280x720.jpg","PTJWVh3Udn1AOB4dUHRNxg==":"structural%20reforms-1280x720.jpg","9+u/k9Yeo7Dx9HwxwAzBeg==":"structural%20reforms-1280x720.jpg","puosKNVg2RDYPKsPRaWlPA==":"structural%20reforms-1086x611.jpg","Hq39Yq1cWTBm4OGH/wt0rw==":"structural%20reforms-1280x720.jpg","WVuKa12K8GWslHA+m4udcw==":"structural%20reforms-1280x720.jpg","HODDSyD++WdnkQUOaPBkeQ==":"mbr-1-1920x1357.jpg"}